asm_practice/__init__.py
asm_practice/__main__.py
asm_practice/coding/__init__.py
asm_practice/coding/challenge.py
asm_practice/coding/driver.py
asm_practice/coding/helpers.py
asm_practice-0.1.0.dist-info/LICENSE
asm_practice-0.1.0.dist-info/WHEEL
asm_practice-0.1.0.dist-info/METADATA
asm_practice-0.1.0.dist-info/RECORD
